{
    "dev": {
        "app_function": "app.handler",
        "profile_name": "default",
        "project_name": "punto2",
        "role_name": "LabRole",
        "runtime": "python3.8",
        "s3_bucket": "zappa-34a644x3d",
        "keep_warm":false,
        "apigateway_enabled":false,
        "manage_roles": false,
        "aws_region": "us-east-1",
        "events": [{
            "function": "app.handler",
            "event_source": {
                  "arn":  "arn:aws:s3:::buckettosaveimagesofanimalsforbigdata",
                  "events": [
                    "s3:ObjectCreated:*"
                  ]
               }
        }]
    }
}